pcileechfwgenerator-2.0.0.dist-info/licenses/LICENSE
src/__init__.py
src/__version__.py
src/advanced_sv_error.py
src/advanced_sv_generator.py
src/advanced_sv_main.py
src/advanced_sv_perf.py
src/advanced_sv_power.py
src/behavior_profiler.py
src/build.py
src/donor_dump_manager.py
src/flash_fpga.py
src/generate_cli.py
src/manufacturing_variance.py
src/state_machine_extractor.py
src/tui_cli.py
src/donor_dump/Makefile
src/donor_dump/README.md
src/donor_dump/donor_dump.c
src/scripts/driver_scrape.py
src/tui/__init__.py
src/tui/main.py
src/tui/core/__init__.py
src/tui/core/build_orchestrator.py
src/tui/core/config_manager.py
src/tui/core/device_manager.py
src/tui/core/status_monitor.py
src/tui/models/__init__.py
src/tui/models/config.py
src/tui/models/device.py
src/tui/models/error.py
src/tui/models/progress.py
src/tui/styles/main.tcss
pcileechfwgenerator-2.0.0.dist-info/METADATA
pcileechfwgenerator-2.0.0.dist-info/WHEEL
pcileechfwgenerator-2.0.0.dist-info/entry_points.txt
pcileechfwgenerator-2.0.0.dist-info/top_level.txt
pcileechfwgenerator-2.0.0.dist-info/RECORD
