Metadata-Version: 2.4
Name: pcileechfwgenerator
Version: 2.0.0
Summary: Generate spoofed PCIe DMA firmware from real donor hardware
Author-email: Ramsey McGrath <ramsey@voltcyclone.info>
Maintainer-email: Ramsey McGrath <ramsey@voltcyclone.info>
License-Expression: MIT
Project-URL: Homepage, https://github.com/ramseymcgrath/PCILeechFWGenerator
Project-URL: Repository, https://github.com/ramseymcgrath/PCILeechFWGenerator
Project-URL: Documentation, https://github.com/ramseymcgrath/PCILeechFWGenerator/blob/main/README.md
Project-URL: Bug Tracker, https://github.com/ramseymcgrath/PCILeechFWGenerator/issues
Project-URL: Changelog, https://github.com/ramseymcgrath/PCILeechFWGenerator/blob/main/CHANGELOG.md
Keywords: pcie,dma,firmware,fpga,hardware,security,penetration-testing,red-team,xilinx,vivado
Classifier: Development Status :: 4 - Beta
Classifier: Environment :: Console
Classifier: Environment :: Console :: Curses
Classifier: Intended Audience :: Developers
Classifier: Intended Audience :: Information Technology
Classifier: Intended Audience :: System Administrators
Classifier: Operating System :: POSIX :: Linux
Classifier: Programming Language :: Python :: 3
Classifier: Programming Language :: Python :: 3.9
Classifier: Programming Language :: Python :: 3.10
Classifier: Programming Language :: Python :: 3.11
Classifier: Programming Language :: Python :: 3.12
Classifier: Topic :: Security
Classifier: Topic :: System :: Hardware
Classifier: Topic :: Software Development :: Embedded Systems
Classifier: Topic :: System :: Systems Administration
Requires-Python: >=3.9
License-File: LICENSE
Requires-Dist: psutil>=5.9.0
Requires-Dist: pydantic>=2.0.0
Provides-Extra: tui
Requires-Dist: textual>=0.45.0; extra == "tui"
Requires-Dist: rich>=13.0.0; extra == "tui"
Requires-Dist: watchdog>=3.0.0; extra == "tui"
Provides-Extra: dev
Requires-Dist: pytest>=7.0.0; extra == "dev"
Requires-Dist: pytest-cov>=4.0.0; extra == "dev"
Requires-Dist: pytest-mock>=3.10.0; extra == "dev"
Requires-Dist: black>=23.0.0; extra == "dev"
Requires-Dist: isort>=5.12.0; extra == "dev"
Requires-Dist: flake8>=6.0.0; extra == "dev"
Requires-Dist: mypy>=1.0.0; extra == "dev"
Requires-Dist: pre-commit>=3.0.0; extra == "dev"
Requires-Dist: build>=0.10.0; extra == "dev"
Requires-Dist: twine>=4.0.0; extra == "dev"
Provides-Extra: test
Requires-Dist: pytest>=7.0.0; extra == "test"
Requires-Dist: pytest-cov>=4.0.0; extra == "test"
Requires-Dist: pytest-mock>=3.10.0; extra == "test"
Requires-Dist: pytest-asyncio>=0.21.0; extra == "test"
Dynamic: license-file
